main.py
mseep_smithery_mcp_python_templates-0.1.1.dist-info/METADATA
mseep_smithery_mcp_python_templates-0.1.1.dist-info/WHEEL
mseep_smithery_mcp_python_templates-0.1.1.dist-info/entry_points.txt
mseep_smithery_mcp_python_templates-0.1.1.dist-info/top_level.txt
mseep_smithery_mcp_python_templates-0.1.1.dist-info/RECORD
